crossmark_jotform_api/__init__.py
crossmark_jotform_api/jotForm.py
crossmark_jotform_api/jotFormSubmission.py
crossmark_jotform_api/types.py
crossmark_jotform_api/utils.py
crossmark_jotform_api-2.6.3.dist-info/licenses/LICENSE
crossmark_jotform_api-2.6.3.dist-info/METADATA
crossmark_jotform_api-2.6.3.dist-info/WHEEL
crossmark_jotform_api-2.6.3.dist-info/top_level.txt
crossmark_jotform_api-2.6.3.dist-info/RECORD
