Metadata-Version: 2.4
Name: crossmark-jotform-api
Version: 2.6.3
Summary: Jotform api integration dedicated for server usage which limits calls and calling form only if there is a new submission
Author-email: Renas Mirkan Kilic <mirkanbaba1@gmail.com>
License: Copyright (c) 2018 The Python Packaging Authority
Project-URL: Homepage, https://github.com/mirkan1/crossmark-jotform-api
Project-URL: Bug Tracker, https://github.com/mirkan1/crossmark-jotform-api/issues
Classifier: Programming Language :: Python :: 3
Classifier: License :: OSI Approved :: MIT License
Classifier: Operating System :: OS Independent
Requires-Python: >=3.8
License-File: LICENSE
Requires-Dist: requests>=2.22.0
Dynamic: license-file
